{
  "tech": [
    {
      "id": "vs-code",
      "name": "Vs Code",
      "icon": {
        "type": "fab",
        "value": "codepen"
      },
      "url": "https://www.facebook.com"
    },
    {
      "id": "sublime-text",
      "name": "Sublime Text",
      "icon": {
        "type": "fab",
        "value": "codepen"
      },
      "url": "https://www.facebook.com"
    },
    {
      "id": "atom",
      "name": "Atom",
      "icon": {
        "type": "fab",
        "value": "codepen"
      },
      "url": "https://www.facebook.com"
    },
    {
      "id": "iterm2",
      "name": "iTerm2",
      "icon": {
        "type": "fab",
        "value": "codepen"
      },
      "url": "https://www.facebook.com"
    },
    {
      "id": "hyper",
      "name": "Hyper",
      "icon": {
        "type": "fab",
        "value": "codepen"
      },
      "url": "https://www.facebook.com"
    },
    {
      "id": "next.js",
      "name": "Next.js",
      "icon": {
        "type": "fab",
        "value": "codepen"
      },
      "url": "https://www.facebook.com"
    },
    {
      "id": "chart.js",
      "name": "Chart.js",
      "icon": {
        "type": "fab",
        "value": "codepen"
      },
      "url": "https://www.facebook.com"
    },
    {
      "id": "github-api",
      "name": "GitHub API",
      "icon": {
        "type": "fab",
        "value": "codepen"
      },
      "url": "https://www.facebook.com"
    },
    {
      "id": "react",
      "name": "React",
      "icon": {
        "type": "fab",
        "value": "codepen"
      },
      "url": "https://www.facebook.com"
    },
    {
      "id": "node.js",
      "name": "Node.js",
      "icon": {
        "type": "fab",
        "value": "codepen"
      },
      "url": "https://www.facebook.com"
    },
    {
      "id": "express",
      "name": "Express",
      "icon": {
        "type": "fab",
        "value": "codepen"
      },
      "url": "https://www.facebook.com"
    },
    {
      "id": "spotify-web-api",
      "name": "Spotify Web API",
      "icon": {
        "type": "fab",
        "value": "codepen"
      },
      "url": "https://www.facebook.com"
    }
  ]
}
